[{"model": "requests.requeststatus", "pk": 1, "fields": {"status": "Новая"}}, {"model": "requests.requeststatus", "pk": 2, "fields": {"status": "Назначена"}}, {"model": "requests.requeststatus", "pk": 3, "fields": {"status": "Не подтверждена"}}, {"model": "requests.requeststatus", "pk": 4, "fields": {"status": "В рассмотрении"}}, {"model": "requests.requeststatus", "pk": 5, "fields": {"status": "Принята"}}, {"model": "requests.requeststatus", "pk": 6, "fields": {"status": "Инспектор выехал"}}, {"model": "requests.requeststatus", "pk": 7, "fields": {"status": "Инспектор на месте"}}, {"model": "requests.requeststatus", "pk": 8, "fields": {"status": "Поездка"}}, {"model": "requests.requeststatus", "pk": 9, "fields": {"status": "Заявка закончена"}}, {"model": "requests.requeststatus", "pk": 10, "fields": {"status": "Выявление"}}, {"model": "requests.requeststatus", "pk": 11, "fields": {"status": "Лист ожидания"}}, {"model": "requests.requeststatus", "pk": 12, "fields": {"status": "Отмена"}}, {"model": "requests.requeststatus", "pk": 13, "fields": {"status": "Отказ"}}, {"model": "requests.requeststatus", "pk": 14, "fields": {"status": "Пассажир опаздывает"}}, {"model": "requests.requeststatus", "pk": 15, "fields": {"status": "Инспектор опаздывает"}}, {"model": "requests.request", "pk": 1, "fields": {"passenger": 19, "category": 10, "status": 1, "description": null, "from_station": 332, "to_station": 350, "date": "2024-06-12", "time_start": "07:13:52", "time_end": "07:51:11", "employee": null}}, {"model": "requests.request", "pk": 3, "fields": {"passenger": 292, "category": 7, "status": 1, "description": null, "from_station": 53, "to_station": 150, "date": "2024-06-12", "time_start": "07:11:24", "time_end": "08:06:44", "employee": null}}, {"model": "requests.request", "pk": 9, "fields": {"passenger": 29, "category": 3, "status": 1, "description": null, "from_station": 37, "to_station": 349, "date": "2024-06-12", "time_start": "07:10:34", "time_end": "07:54:50", "employee": null}}, {"model": "requests.request", "pk": 19, "fields": {"passenger": 44, "category": 10, "status": 1, "description": null, "from_station": 363, "to_station": 38, "date": "2024-06-12", "time_start": "07:13:01", "time_end": "07:31:04", "employee": null}}, {"model": "requests.request", "pk": 25, "fields": {"passenger": 237, "category": 6, "status": 1, "description": null, "from_station": 131, "to_station": 104, "date": "2024-06-12", "time_start": "07:20:00", "time_end": "07:58:00", "employee": null}}, {"model": "requests.request", "pk": 26, "fields": {"passenger": 16, "category": 9, "status": 1, "description": null, "from_station": 284, "to_station": 121, "date": "2024-06-12", "time_start": "07:32:00", "time_end": "08:24:00", "employee": null}}, {"model": "requests.request", "pk": 40, "fields": {"passenger": 259, "category": 2, "status": 1, "description": null, "from_station": 272, "to_station": 186, "date": "2024-06-12", "time_start": "07:50:00", "time_end": "07:59:41", "employee": null}}, {"model": "requests.request", "pk": 58, "fields": {"passenger": 234, "category": 3, "status": 1, "description": null, "from_station": 124, "to_station": 84, "date": "2024-06-12", "time_start": "07:23:50", "time_end": "08:01:38", "employee": null}}, {"model": "requests.request", "pk": 63, "fields": {"passenger": 204, "category": 3, "status": 1, "description": null, "from_station": 399, "to_station": 182, "date": "2024-06-12", "time_start": "07:58:38", "time_end": "08:34:19", "employee": null}}, {"model": "requests.request", "pk": 67, "fields": {"passenger": 162, "category": 9, "status": 1, "description": null, "from_station": 395, "to_station": 393, "date": "2024-06-12", "time_start": "07:53:22", "time_end": "08:28:00", "employee": null}}, {"model": "requests.request", "pk": 82, "fields": {"passenger": 283, "category": 2, "status": 1, "description": null, "from_station": 12, "to_station": 229, "date": "2024-06-12", "time_start": "07:33:11", "time_end": "08:02:44", "employee": null}}, {"model": "requests.request", "pk": 103, "fields": {"passenger": 113, "category": 2, "status": 1, "description": null, "from_station": 195, "to_station": 180, "date": "2024-06-12", "time_start": "07:43:50", "time_end": "08:07:48", "employee": null}}, {"model": "requests.request", "pk": 114, "fields": {"passenger": 68, "category": 2, "status": 1, "description": null, "from_station": 219, "to_station": 191, "date": "2024-06-12", "time_start": "07:09:35", "time_end": "07:55:36", "employee": null}}, {"model": "requests.request", "pk": 121, "fields": {"passenger": 132, "category": 6, "status": 1, "description": null, "from_station": 235, "to_station": 386, "date": "2024-06-12", "time_start": "07:48:07", "time_end": "08:29:07", "employee": null}}, {"model": "requests.request", "pk": 138, "fields": {"passenger": 154, "category": 4, "status": 1, "description": null, "from_station": 382, "to_station": 225, "date": "2024-06-12", "time_start": "07:01:59", "time_end": "08:14:29", "employee": null}}, {"model": "requests.request", "pk": 147, "fields": {"passenger": 127, "category": 10, "status": 1, "description": null, "from_station": 227, "to_station": 218, "date": "2024-06-12", "time_start": "07:57:25", "time_end": "08:41:18", "employee": null}}, {"model": "requests.request", "pk": 159, "fields": {"passenger": 230, "category": 5, "status": 1, "description": null, "from_station": 268, "to_station": 64, "date": "2024-06-12", "time_start": "07:20:29", "time_end": "08:12:07", "employee": null}}, {"model": "requests.request", "pk": 168, "fields": {"passenger": 51, "category": 10, "status": 1, "description": null, "from_station": 415, "to_station": 94, "date": "2024-06-12", "time_start": "07:13:37", "time_end": "08:01:33", "employee": null}}, {"model": "requests.request", "pk": 181, "fields": {"passenger": 48, "category": 1, "status": 1, "description": null, "from_station": 180, "to_station": 148, "date": "2024-06-12", "time_start": "07:14:17", "time_end": "07:57:42", "employee": null}}, {"model": "requests.request", "pk": 204, "fields": {"passenger": 49, "category": 5, "status": 1, "description": null, "from_station": 62, "to_station": 128, "date": "2024-06-12", "time_start": "07:41:33", "time_end": "09:10:20", "employee": null}}, {"model": "requests.request", "pk": 206, "fields": {"passenger": 172, "category": 1, "status": 1, "description": null, "from_station": 76, "to_station": 44, "date": "2024-06-12", "time_start": "07:06:25", "time_end": "07:40:58", "employee": null}}, {"model": "requests.request", "pk": 213, "fields": {"passenger": 237, "category": 9, "status": 1, "description": null, "from_station": 94, "to_station": 241, "date": "2024-06-12", "time_start": "07:40:50", "time_end": "08:30:13", "employee": null}}, {"model": "requests.request", "pk": 215, "fields": {"passenger": 2, "category": 5, "status": 1, "description": null, "from_station": 397, "to_station": 62, "date": "2024-06-12", "time_start": "07:59:03", "time_end": "08:17:42", "employee": null}}, {"model": "requests.request", "pk": 234, "fields": {"passenger": 19, "category": 10, "status": 1, "description": null, "from_station": 332, "to_station": 350, "date": "2024-06-13", "time_start": "08:13:52", "time_end": "08:51:11", "employee": null}}, {"model": "requests.request", "pk": 235, "fields": {"passenger": 292, "category": 7, "status": 1, "description": null, "from_station": 53, "to_station": 150, "date": "2024-06-12", "time_start": "08:11:24", "time_end": "09:06:44", "employee": null}}, {"model": "requests.request", "pk": 236, "fields": {"passenger": 29, "category": 3, "status": 1, "description": null, "from_station": 37, "to_station": 349, "date": "2024-06-12", "time_start": "08:10:34", "time_end": "08:54:50", "employee": null}}, {"model": "requests.request", "pk": 237, "fields": {"passenger": 44, "category": 10, "status": 1, "description": null, "from_station": 363, "to_station": 38, "date": "2024-06-12", "time_start": "08:13:01", "time_end": "08:31:04", "employee": null}}, {"model": "requests.request", "pk": 238, "fields": {"passenger": 237, "category": 6, "status": 1, "description": null, "from_station": 131, "to_station": 104, "date": "2024-06-12", "time_start": "08:20:00", "time_end": "08:58:00", "employee": null}}, {"model": "requests.request", "pk": 239, "fields": {"passenger": 16, "category": 9, "status": 1, "description": null, "from_station": 284, "to_station": 121, "date": "2024-06-12", "time_start": "08:32:00", "time_end": "09:24:00", "employee": null}}, {"model": "requests.request", "pk": 240, "fields": {"passenger": 259, "category": 2, "status": 1, "description": null, "from_station": 272, "to_station": 186, "date": "2024-06-12", "time_start": "08:50:00", "time_end": "08:59:41", "employee": null}}, {"model": "requests.request", "pk": 241, "fields": {"passenger": 234, "category": 3, "status": 1, "description": null, "from_station": 124, "to_station": 84, "date": "2024-06-12", "time_start": "08:23:50", "time_end": "09:01:38", "employee": null}}, {"model": "requests.request", "pk": 242, "fields": {"passenger": 204, "category": 3, "status": 1, "description": null, "from_station": 399, "to_station": 182, "date": "2024-06-12", "time_start": "08:58:38", "time_end": "09:34:19", "employee": null}}, {"model": "requests.request", "pk": 243, "fields": {"passenger": 162, "category": 9, "status": 1, "description": null, "from_station": 395, "to_station": 393, "date": "2024-06-12", "time_start": "08:53:22", "time_end": "09:28:00", "employee": null}}, {"model": "requests.request", "pk": 244, "fields": {"passenger": 283, "category": 2, "status": 1, "description": null, "from_station": 12, "to_station": 229, "date": "2024-06-12", "time_start": "08:33:11", "time_end": "09:02:44", "employee": null}}, {"model": "requests.request", "pk": 245, "fields": {"passenger": 113, "category": 2, "status": 1, "description": null, "from_station": 195, "to_station": 180, "date": "2024-06-12", "time_start": "08:43:50", "time_end": "09:07:48", "employee": null}}, {"model": "requests.request", "pk": 246, "fields": {"passenger": 68, "category": 2, "status": 1, "description": null, "from_station": 219, "to_station": 191, "date": "2024-06-12", "time_start": "08:09:35", "time_end": "08:55:36", "employee": null}}, {"model": "requests.request", "pk": 247, "fields": {"passenger": 132, "category": 6, "status": 1, "description": null, "from_station": 235, "to_station": 386, "date": "2024-06-12", "time_start": "08:48:07", "time_end": "09:29:07", "employee": null}}, {"model": "requests.request", "pk": 248, "fields": {"passenger": 154, "category": 4, "status": 1, "description": null, "from_station": 382, "to_station": 225, "date": "2024-06-12", "time_start": "08:01:59", "time_end": "09:14:29", "employee": null}}, {"model": "requests.request", "pk": 249, "fields": {"passenger": 127, "category": 10, "status": 1, "description": null, "from_station": 227, "to_station": 218, "date": "2024-06-12", "time_start": "08:57:25", "time_end": "09:41:18", "employee": null}}, {"model": "requests.request", "pk": 250, "fields": {"passenger": 230, "category": 5, "status": 1, "description": null, "from_station": 268, "to_station": 64, "date": "2024-06-12", "time_start": "08:20:29", "time_end": "09:12:07", "employee": null}}, {"model": "requests.request", "pk": 251, "fields": {"passenger": 51, "category": 10, "status": 1, "description": null, "from_station": 415, "to_station": 94, "date": "2024-06-12", "time_start": "08:13:37", "time_end": "09:01:33", "employee": null}}, {"model": "requests.request", "pk": 252, "fields": {"passenger": 48, "category": 1, "status": 1, "description": null, "from_station": 180, "to_station": 148, "date": "2024-06-12", "time_start": "08:14:17", "time_end": "08:57:42", "employee": null}}, {"model": "requests.request", "pk": 253, "fields": {"passenger": 49, "category": 5, "status": 1, "description": null, "from_station": 62, "to_station": 128, "date": "2024-06-12", "time_start": "08:41:33", "time_end": "10:10:20", "employee": null}}, {"model": "requests.request", "pk": 254, "fields": {"passenger": 172, "category": 1, "status": 1, "description": null, "from_station": 76, "to_station": 44, "date": "2024-06-12", "time_start": "08:06:25", "time_end": "08:40:58", "employee": null}}, {"model": "requests.request", "pk": 255, "fields": {"passenger": 237, "category": 9, "status": 1, "description": null, "from_station": 94, "to_station": 241, "date": "2024-06-12", "time_start": "08:40:50", "time_end": "09:30:13", "employee": null}}, {"model": "requests.request", "pk": 256, "fields": {"passenger": 2, "category": 5, "status": 1, "description": null, "from_station": 397, "to_station": 62, "date": "2024-06-12", "time_start": "08:59:03", "time_end": "09:17:42", "employee": null}}, {"model": "requests.request", "pk": 257, "fields": {"passenger": 83, "category": 9, "status": 1, "description": null, "from_station": 328, "to_station": 395, "date": "2024-06-12", "time_start": "08:58:31", "time_end": "10:02:10", "employee": null}}, {"model": "requests.request", "pk": 278, "fields": {"passenger": 83, "category": 9, "status": 1, "description": null, "from_station": 328, "to_station": 395, "date": "2024-06-12", "time_start": "07:58:31", "time_end": "09:02:10", "employee": null}}]